MenuCreator/MenuCreator.py
MenuCreator/__init__.py
Menu_Creator-0.1.7.dist-info/LICENSE
Menu_Creator-0.1.7.dist-info/METADATA
Menu_Creator-0.1.7.dist-info/WHEEL
Menu_Creator-0.1.7.dist-info/top_level.txt
Menu_Creator-0.1.7.dist-info/RECORD
